rotavision_guardian/__init__.py
rotavision_guardian-0.0.1.dist-info/METADATA
rotavision_guardian-0.0.1.dist-info/WHEEL
rotavision_guardian-0.0.1.dist-info/RECORD
