Metadata-Version: 2.4
Name: rotavision-guardian
Version: 0.0.1
Summary: Rotavision Guardian - AI Reliability Monitoring
Project-URL: Homepage, https://rotavision.com
Project-URL: Documentation, https://rotavision.com/docs
Project-URL: Repository, https://github.com/rotavision-ai/python-sdk
Author-email: Rotavision <developers@rotavision.com>
License-Expression: Apache-2.0
Keywords: ai,fairness,governance,india,rotavision,trust
Classifier: Development Status :: 1 - Planning
Classifier: Intended Audience :: Developers
Classifier: License :: OSI Approved :: Apache Software License
Classifier: Programming Language :: Python :: 3
Requires-Python: >=3.8
